PadoKao1.py
PadoKao2.py
PadoKao3.py
__main__.py
feed.py
PadiKao-1.0.0.dist-info/LICENSE.txt
PadiKao-1.0.0.dist-info/METADATA
PadiKao-1.0.0.dist-info/WHEEL
PadiKao-1.0.0.dist-info/entry_points.txt
PadiKao-1.0.0.dist-info/top_level.txt
PadiKao-1.0.0.dist-info/RECORD
