Metadata-Version: 2.1
Name: PadiKao
Version: 1.0.0
Summary: Read the latest RaNaCl tutorials
Author-email: RaNaCl <info@realpython.com>
Project-URL: Homepage, https://github.com/realpython/reader
Keywords: feed,reader,tutorial
Classifier: License :: OSI Approved :: MIT License
Classifier: Programming Language :: Python
Classifier: Programming Language :: Python :: 3
Requires-Python: >=3.0
License-File: LICENSE.txt
Requires-Dist: tomli ; python_version < "3.12"
Provides-Extra: dev
Requires-Dist: black ; extra == 'dev'
Requires-Dist: bumpver ; extra == 'dev'
Requires-Dist: isort ; extra == 'dev'
Requires-Dist: pip-tools ; extra == 'dev'
Requires-Dist: pytest ; extra == 'dev'
